MANIFEST.in
README.rst
pytest.ini
requirements.txt
setup.py
tox.ini
pysnowflake.egg-info/PKG-INFO
pysnowflake.egg-info/SOURCES.txt
pysnowflake.egg-info/dependency_links.txt
pysnowflake.egg-info/entry_points.txt
pysnowflake.egg-info/not-zip-safe
pysnowflake.egg-info/requires.txt
pysnowflake.egg-info/top_level.txt
snowflake/__init__.py
snowflake/client/__init__.py
snowflake/server/__init__.py
snowflake/server/generator.py
snowflake/server/logging.ini