Metadata-Version: 1.1
Name: pysnowflake
Version: 0.1.2
Summary: Python Snowflake Kit
Home-page: https://github.com/tarzanjw/pysnowflake
Author: Học .T Đỗ
Author-email: hoc3010@gmail.com
License: UNKNOWN
Keywords: snowflake server client
Platform: UNKNOWN
Classifier: Programming Language :: Python
Classifier: Programming Language :: Python :: 2.7
Classifier: Programming Language :: Python :: 3
Classifier: Topic :: Utilities
Classifier: Topic :: Software Development :: Libraries
